oscars_toolbox/__init__.py
oscars_toolbox/implement_torch.py
oscars_toolbox/implement_xgb.py
oscars_toolbox/sample.py
oscars_toolbox/torch_models.py
oscars_toolbox/trabbit.py
oscars_toolbox-0.1.9.dist-info/LICENSE
oscars_toolbox-0.1.9.dist-info/METADATA
oscars_toolbox-0.1.9.dist-info/WHEEL
oscars_toolbox-0.1.9.dist-info/top_level.txt
oscars_toolbox-0.1.9.dist-info/RECORD
