Metadata-Version: 2.1
Name: oscars_toolbox
Version: 0.1.9
Summary: A package for optimization. See the GitHub repo for instructions and version notes.
Author-email: Oscar Scholin <scholinoscar@gmail.com>
Project-URL: Homepage, https://github.com/oscars47/oscars-toolbox
Project-URL: Issues, https://github.com/oscars47/oscars-toolbox/issues
Classifier: Programming Language :: Python :: 3
Classifier: License :: OSI Approved :: MIT License
Classifier: Operating System :: OS Independent
Requires-Python: >=3.8
License-File: LICENSE
